[
 {
   "FIELD1": "ETC_NetHope_UID",
   "FIELD2": "NetHope_ConnReqNum",
   "FIELD3": "Project_Group",
   "FIELD4": "Org_name",
   "FIELD5": "Country",
   "FIELD6": "Location_name",
   "FIELD7": "Location_type",
   "FIELD8": "Admin1",
   "FIELD9": "Admin2",
   "FIELD10": "Admin3",
   "FIELD11": "PCODEs",
   "FIELD12": "LatLLong_Confirmed",
   "FIELD13": "Latitude",
   "FIELD14": "Longitude",
   "FIELD15": "Service_Type",
   "FIELD16": "Service_Status",
   "FIELD17": "Internet_Capacity",
   "FIELD18": "Contact_Name",
   "FIELD19": "Contact_e-address",
   "FIELD20": "Contact_address",
   "FIELD21": "Contact_Tel",
   "FIELD22": "Editor",
   "FIELD23": "Edit_date",
   "FIELD24": "GISCorp_Comments",
   "FIELD25": "Connectivity_type",
   "FIELD26": "Distribution_network_type",
   "FIELD27": "Radio_connectivity_type",
   "FIELD28": "Up_speed",
   "FIELD29": "Down_speed",
   "FIELD30": "Electrical_service",
   "FIELD31": "Radio_room_type",
   "FIELD32": "Service_providers",
   "FIELD33": "Vehicles with radios"
 },
 {
   "FIELD1": "",
   "FIELD2": "",
   "FIELD3": "2",
   "FIELD4": "NGO",
   "FIELD5": "GIN",
   "FIELD6": "Coyah ETU",
   "FIELD7": "ETU",
   "FIELD8": "Coyah",
   "FIELD9": "Coyah",
   "FIELD10": "\n",
   "FIELD11": "",
   "FIELD12": "N",
   "FIELD13": "",
   "FIELD14": "",
   "FIELD15": "NGO radio coms",
   "FIELD16": "PLANNED",
   "FIELD17": "",
   "FIELD18": "rob buurveld",
   "FIELD19": "rob.buurveld@wfp.org",
   "FIELD20": "",
   "FIELD21": "",
   "FIELD22": "MR",
   "FIELD23": "",
   "FIELD24": "",
   "FIELD25": "",
   "FIELD26": "",
   "FIELD27": "",
   "FIELD28": "",
   "FIELD29": "",
   "FIELD30": "",
   "FIELD31": "",
   "FIELD32": "NetHope",
   "FIELD33": ""
 },
 {
   "FIELD1": "079",
   "FIELD2": "",
   "FIELD3": "2",
   "FIELD4": "WAHA ETU",
   "FIELD5": "GIN",
   "FIELD6": "Beyla",
   "FIELD7": "ETU",
   "FIELD8": "Beyla",
   "FIELD9": "",
   "FIELD10": "",
   "FIELD11": "",
   "FIELD12": "Y",
   "FIELD13": "8.4043\n",
   "FIELD14": "-8.382644\n",
   "FIELD15": "NGO radio coms",
   "FIELD16": "PLANNED",
   "FIELD17": "",
   "FIELD18": "rob buurveld",
   "FIELD19": "rob.buurveld@wfp.org",
   "FIELD20": "",
   "FIELD21": "",
   "FIELD22": "MR",
   "FIELD23": "12/24/2014",
   "FIELD24": "VERIFIED  8°24'15.48\"N ,\n\n8°22'57.72\"W ",
   "FIELD25": "",
   "FIELD26": "",
   "FIELD27": "",
   "FIELD28": "",
   "FIELD29": "",
   "FIELD30": "",
   "FIELD31": "",
   "FIELD32": "",
   "FIELD33": ""
 },
 {
   "FIELD1": "054",
   "FIELD2": "",
   "FIELD3": "2",
   "FIELD4": "WFP",
   "FIELD5": "GIN",
   "FIELD6": "Conakry",
   "FIELD7": "Radio coms",
   "FIELD8": "Conakry",
   "FIELD9": "",
   "FIELD10": "",
   "FIELD11": "",
   "FIELD12": "N",
   "FIELD13": "NA",
   "FIELD14": "NA",
   "FIELD15": "UN radio coms",
   "FIELD16": "OPEN",
   "FIELD17": "",
   "FIELD18": "Rob BUURVELD",
   "FIELD19": "rob.buurveld@wfp.org",
   "FIELD20": "",
   "FIELD21": "",
   "FIELD22": "MR",
   "FIELD23": "12/24/2014",
   "FIELD24": "",
   "FIELD25": "",
   "FIELD26": "",
   "FIELD27": "Upgrade Repeater",
   "FIELD28": "",
   "FIELD29": "",
   "FIELD30": "",
   "FIELD31": "24x7",
   "FIELD32": "",
   "FIELD33": ""
 },
 {
   "FIELD1": "055",
   "FIELD2": "",
   "FIELD3": "2",
   "FIELD4": "WFP",
   "FIELD5": "GIN",
   "FIELD6": "Conakry",
   "FIELD7": "Radio coms",
   "FIELD8": "Conakry",
   "FIELD9": "",
   "FIELD10": "",
   "FIELD11": "",
   "FIELD12": "N",
   "FIELD13": "NA",
   "FIELD14": "NA",
   "FIELD15": "NGO radio coms",
   "FIELD16": "OPEN",
   "FIELD17": "",
   "FIELD18": "Rob BUURVELD",
   "FIELD19": "rob.buurveld@wfp.org",
   "FIELD20": "",
   "FIELD21": "",
   "FIELD22": "MR",
   "FIELD23": "12/24/2014",
   "FIELD24": "",
   "FIELD25": "",
   "FIELD26": "",
   "FIELD27": "Upgrade Repeater",
   "FIELD28": "",
   "FIELD29": "",
   "FIELD30": "",
   "FIELD31": "24x7",
   "FIELD32": "",
   "FIELD33": ""
 },
 {
   "FIELD1": "056",
   "FIELD2": "",
   "FIELD3": "2",
   "FIELD4": "WFP",
   "FIELD5": "GIN",
   "FIELD6": "Kissidougou",
   "FIELD7": "Radio coms",
   "FIELD8": "Kissidougou",
   "FIELD9": "",
   "FIELD10": "",
   "FIELD11": "",
   "FIELD12": "N",
   "FIELD13": "NA",
   "FIELD14": "NA",
   "FIELD15": "UN radio coms",
   "FIELD16": "OPEN",
   "FIELD17": "",
   "FIELD18": "Rob Buurveld",
   "FIELD19": "rob.buurveld@wfp.org",
   "FIELD20": "",
   "FIELD21": "",
   "FIELD22": "MR",
   "FIELD23": "12/24/2014",
   "FIELD24": "",
   "FIELD25": "",
   "FIELD26": "",
   "FIELD27": "New Repeater",
   "FIELD28": "",
   "FIELD29": "",
   "FIELD30": "",
   "FIELD31": "24x7",
   "FIELD32": "",
   "FIELD33": ""
 },
 {
   "FIELD1": "057",
   "FIELD2": "",
   "FIELD3": "2",
   "FIELD4": "WFP",
   "FIELD5": "GIN",
   "FIELD6": "Kissidougou",
   "FIELD7": "Radio coms",
   "FIELD8": "Kissidougou",
   "FIELD9": "",
   "FIELD10": "",
   "FIELD11": "",
   "FIELD12": "N",
   "FIELD13": "NA",
   "FIELD14": "NA",
   "FIELD15": "NGO radio coms",
   "FIELD16": "OPEN",
   "FIELD17": "",
   "FIELD18": "rob buurveld",
   "FIELD19": "rob.buurveld@wfp.org",
   "FIELD20": "",
   "FIELD21": "",
   "FIELD22": "MR",
   "FIELD23": "12/24/2014",
   "FIELD24": "",
   "FIELD25": "",
   "FIELD26": "",
   "FIELD27": "New Repeater",
   "FIELD28": "",
   "FIELD29": "",
   "FIELD30": "",
   "FIELD31": "24x7",
   "FIELD32": "",
   "FIELD33": ""
 },
 {
   "FIELD1": "058",
   "FIELD2": "",
   "FIELD3": "2",
   "FIELD4": "WFP",
   "FIELD5": "GIN",
   "FIELD6": "Gueckedou",
   "FIELD7": "Radio coms",
   "FIELD8": "Gueckedou",
   "FIELD9": "",
   "FIELD10": "",
   "FIELD11": "",
   "FIELD12": "N",
   "FIELD13": "NA",
   "FIELD14": "NA",
   "FIELD15": "UN radio coms",
   "FIELD16": "OPEN",
   "FIELD17": "",
   "FIELD18": "rob buurveld",
   "FIELD19": "rob.buurveld@wfp.org",
   "FIELD20": "",
   "FIELD21": "",
   "FIELD22": "MR",
   "FIELD23": "12/24/2014",
   "FIELD24": "",
   "FIELD25": "",
   "FIELD26": "",
   "FIELD27": "Upgrade Repeater",
   "FIELD28": "",
   "FIELD29": "",
   "FIELD30": "",
   "FIELD31": "24x7",
   "FIELD32": "",
   "FIELD33": ""
 },
 {
   "FIELD1": "059",
   "FIELD2": "",
   "FIELD3": "2",
   "FIELD4": "WFP",
   "FIELD5": "GIN",
   "FIELD6": "Gueckedou",
   "FIELD7": "Radio coms",
   "FIELD8": "Gueckedou",
   "FIELD9": "",
   "FIELD10": "",
   "FIELD11": "",
   "FIELD12": "N",
   "FIELD13": "NA",
   "FIELD14": "NA",
   "FIELD15": "NGO radio coms",
   "FIELD16": "OPEN",
   "FIELD17": "",
   "FIELD18": "rob buurveld",
   "FIELD19": "rob.buurveld@wfp.org",
   "FIELD20": "",
   "FIELD21": "",
   "FIELD22": "MR",
   "FIELD23": "12/24/2014",
   "FIELD24": "",
   "FIELD25": "",
   "FIELD26": "",
   "FIELD27": "Upgrade Repeater",
   "FIELD28": "",
   "FIELD29": "",
   "FIELD30": "",
   "FIELD31": "8x5",
   "FIELD32": "",
   "FIELD33": ""
 },
 {
   "FIELD1": "060",
   "FIELD2": "",
   "FIELD3": "2",
   "FIELD4": "WFP",
   "FIELD5": "GIN",
   "FIELD6": "Macenta",
   "FIELD7": "Radio coms",
   "FIELD8": "Macenta",
   "FIELD9": "",
   "FIELD10": "",
   "FIELD11": "",
   "FIELD12": "N",
   "FIELD13": "NA",
   "FIELD14": "NA",
   "FIELD15": "UN radio coms",
   "FIELD16": "PLANNED",
   "FIELD17": "",
   "FIELD18": "rob buurveld",
   "FIELD19": "rob.buurveld@wfp.org",
   "FIELD20": "",
   "FIELD21": "",
   "FIELD22": "MR",
   "FIELD23": "12/24/2014",
   "FIELD24": "",
   "FIELD25": "",
   "FIELD26": "",
   "FIELD27": "Upgrade Repeater",
   "FIELD28": "",
   "FIELD29": "",
   "FIELD30": "",
   "FIELD31": "8x5",
   "FIELD32": "",
   "FIELD33": ""
 },
 {
   "FIELD1": "061",
   "FIELD2": "",
   "FIELD3": "2",
   "FIELD4": "WFP",
   "FIELD5": "GIN",
   "FIELD6": "Macenta",
   "FIELD7": "Radio coms",
   "FIELD8": "Macenta",
   "FIELD9": "",
   "FIELD10": "",
   "FIELD11": "",
   "FIELD12": "N",
   "FIELD13": "NA",
   "FIELD14": "NA",
   "FIELD15": "NGO radio coms",
   "FIELD16": "PLANNED",
   "FIELD17": "",
   "FIELD18": "rob buurveld",
   "FIELD19": "rob.buurveld@wfp.org",
   "FIELD20": "",
   "FIELD21": "",
   "FIELD22": "MR",
   "FIELD23": "12/24/2014",
   "FIELD24": "",
   "FIELD25": "",
   "FIELD26": "",
   "FIELD27": "Upgrade Repeater",
   "FIELD28": "",
   "FIELD29": "",
   "FIELD30": "",
   "FIELD31": "8x5",
   "FIELD32": "",
   "FIELD33": ""
 },
 {
   "FIELD1": "069",
   "FIELD2": "",
   "FIELD3": "2",
   "FIELD4": "WFP",
   "FIELD5": "GIN",
   "FIELD6": "Nzerekore",
   "FIELD7": "Radio coms",
   "FIELD8": "Nzerekore",
   "FIELD9": "",
   "FIELD10": "",
   "FIELD11": "",
   "FIELD12": "N",
   "FIELD13": "NA",
   "FIELD14": "NA",
   "FIELD15": "UN radio coms",
   "FIELD16": "OPEN",
   "FIELD17": "",
   "FIELD18": "rob buurveld",
   "FIELD19": "rob.buurveld@wfp.org",
   "FIELD20": "",
   "FIELD21": "",
   "FIELD22": "MR",
   "FIELD23": "12/24/2014",
   "FIELD24": "",
   "FIELD25": "",
   "FIELD26": "",
   "FIELD27": "Upgrade Repeater",
   "FIELD28": "",
   "FIELD29": "",
   "FIELD30": "",
   "FIELD31": "24x7",
   "FIELD32": "",
   "FIELD33": ""
 },
 {
   "FIELD1": "070",
   "FIELD2": "",
   "FIELD3": "2",
   "FIELD4": "WFP",
   "FIELD5": "GIN",
   "FIELD6": "Nzerekore",
   "FIELD7": "Radio coms",
   "FIELD8": "Nzerekore",
   "FIELD9": "",
   "FIELD10": "",
   "FIELD11": "",
   "FIELD12": "N",
   "FIELD13": "NA",
   "FIELD14": "NA",
   "FIELD15": "NGO radio coms",
   "FIELD16": "OPEN",
   "FIELD17": "",
   "FIELD18": "rob buurveld",
   "FIELD19": "rob.buurveld@wfp.org",
   "FIELD20": "",
   "FIELD21": "",
   "FIELD22": "MR",
   "FIELD23": "12/24/2014",
   "FIELD24": "",
   "FIELD25": "",
   "FIELD26": "",
   "FIELD27": "Upgrade Repeater",
   "FIELD28": "",
   "FIELD29": "",
   "FIELD30": "",
   "FIELD31": "24x7",
   "FIELD32": "",
   "FIELD33": ""
 }
]